aiZero_gr/__init__.py
aiZero_gr-0.0.3a3.dist-info/METADATA
aiZero_gr-0.0.3a3.dist-info/WHEEL
aiZero_gr-0.0.3a3.dist-info/top_level.txt
aiZero_gr-0.0.3a3.dist-info/RECORD
