Metadata-Version: 2.1
Name: aiZero-gr
Version: 0.0.3a3
Summary: A simple and easy-to-use library that connects to common artificial intelligence interfaces (powered by Gradio), allowing for quick development of local web applications. It includes mainstream AI capabilities such as LLM text interaction, image understanding, audio understanding, image generation, speech recognition, and speech synthesis.
Home-page: UNKNOWN
Author: emhang
Author-email: emhang@126.com
License: UNKNOWN
Platform: UNKNOWN
Requires-Python: >=3.10
Requires-Dist: gradio (>=5.5.0)
Requires-Dist: requests
Requires-Dist: dashscope (>=1.20.0)
